watch_diff/__init__.py
watch_diff/__main__.py
watch_diff/command.py
watch_diff/diff.py
watch_diff/email.py
watch_diff/format.py
watch_diff-1.1.4.dist-info/LICENSE
watch_diff-1.1.4.dist-info/METADATA
watch_diff-1.1.4.dist-info/WHEEL
watch_diff-1.1.4.dist-info/entry_points.txt
watch_diff-1.1.4.dist-info/top_level.txt
watch_diff-1.1.4.dist-info/RECORD
