Metadata-Version: 2.1
Name: watch-diff
Version: 1.1.4
Summary: Watch command output and get notified on changes
Home-page: https://github.com/francisbergin/watch-diff
Author: francisbergin
Author-email: francisbergin@hotmail.com
License: MIT
Requires-Python: >=3.7
License-File: LICENSE
Provides-Extra: dev
Requires-Dist: black (==23.1.0) ; extra == 'dev'
Requires-Dist: setuptools (==67.4.0) ; extra == 'dev'
Requires-Dist: tox (==4.4.6) ; extra == 'dev'
Requires-Dist: twine (==4.0.2) ; extra == 'dev'
Requires-Dist: wheel (==0.38.4) ; extra == 'dev'
